zabbix_sys/__init__.py
zabbix_sys/cli.py
zabbix_sys/svc/__init__.py
zabbix_sys/svc/elastic.py
zabbix_sys/svc/mysql.py
zabbix_sys/svc/nginx.py
zabbix_sys/svc/rabbitmq.py
zabbix_sys/svc/redis.py
zabbix_sys/svc/system.py
zabbix_sys/tools/__init__.py
zabbix_sys/tools/config.py
zabbix_sys/tools/console.py
zabbix_sys/tools/logger.py
zabbix_sys-2021.9.1.1630515474.dist-info/LICENSE
zabbix_sys-2021.9.1.1630515474.dist-info/METADATA
zabbix_sys-2021.9.1.1630515474.dist-info/WHEEL
zabbix_sys-2021.9.1.1630515474.dist-info/entry_points.txt
zabbix_sys-2021.9.1.1630515474.dist-info/top_level.txt
zabbix_sys-2021.9.1.1630515474.dist-info/RECORD
